client/__init__.py
client/client.py
client/client/__init__.py
client/client/add_contact.py
client/client/client_database.py
client/client/del_contact.py
client/client/main_window.py
client/client/main_window_conv.py
client/client/start_dialog.py
client/client/transport.py
client/common/__init__.py
client/common/decorator.py
client/common/descript.py
client/common/errors.py
client/common/metaclasses.py
client/common/utils.py
client/common/variables.py
client/log/__init__.py
client/log/logs_config/__init__.py
client/log/logs_config/client_config.py
client/log/logs_config/server_config.py
client/tests/__init__.py
client/tests/client_test.py
client/tests/server_test.py
client/tests/utils-test.py
mess_client_project46-0.0.1.dist-info/METADATA
mess_client_project46-0.0.1.dist-info/WHEEL
mess_client_project46-0.0.1.dist-info/top_level.txt
mess_client_project46-0.0.1.dist-info/RECORD
